ED/Guía 5/Ej3/T.v
module T (
   input clk, t, rst,
   output reg q
);

always @(posedge clk) begin
    case(t)
        1'b1 : q=~q;
        1'b0 : q=q;
    endcase
end

always @(posedge rst) begin
    q=0;
end

endmodule

ED/Guía 5/Ej3/T_tb.v
`default_nettype none
`define DUMPSTR(x) `"x.vcd`"
`timescale 100 ns / 10 ns //Define la unidad de tiempo

module T_tb();
    
    parameter DURATION = 10;

    reg clk, t, rst;
    wire q;

    T UUT(
        .clk(clk),
        .rst(rst),
        .t(t),
        .q(q)
        
    );

    always #5 clk = !clk;
    always #3 t = t + 1;


    initial begin
        
        $dumpfile(`DUMPSTR(`VCD_OUTPUT));
        $dumpvars(0, T_tb);

        #(DURATION) $display("Fin de la simulación.");  
        clk = 0;
        rst = 1;
        t=0;
        #100;      
        $finish;

    end

endmodule

ED/Guía 5/Ej3/T_tb.vcd
$date
	Wed May 22 15:29:10 2024
$end
$version
	Icarus Verilog
$end
$timescale
	1ps
$end
$scope module T_tb $end
$var wire 1 ! q $end
$var parameter 32 " DURATION $end
$var reg 1 # clk $end
$var reg 1 $ rst $end
$var reg 1 % t $end
$scope module UUT $end
$var wire 1 # clk $end
$var wire 1 $ rst $end
$var wire 1 % t $end
$var reg 1 ! q $end
$upscope $end
$upscope $end
$enddefinitions $end
$comment Show the parameter values. $end
$dumpall
b1010 "
$end
#0
$dumpvars
x%
x$
x#
x!
$end
#1000000
0!
0%
1$
1#
#1200000
1%
#1500000
0%
0#
#1800000
1%
#2000000
1!
1#
#2100000
0%
#2400000
1%
#2500000
0#
#2700000
0%
#3000000
0!
1%
1#
#3300000
0%
#3500000
0#
#3600000
1%
#3900000
0%
#4000000
1#
#4200000
1%
#4500000
0%
0#
#4800000
1%
#5000000
1!
1#
#5100000
0%
#5400000
1%
#5500000
0#
#5700000
0%
#6000000
0!
1%
1#
#6300000
0%
#6500000
0#
#6600000
1%
#6900000
0%
#7000000
1#
#7200000
1%
#7500000
0%
0#
#7800000
1%
#8000000
1!
1#
#8100000
0%
#8400000
1%
#8500000
0#
#8700000
0%
#9000000
0!
1%
1#
#9300000
0%
#9500000
0#
#9600000
1%
#9900000
0%
#10000000
1#
#10200000
1%
#10500000
0%
0#
#10800000
1%
#11000000
1!
1#
